Workbook

Sheet Índice
A1: Bonos y TIR · serie 2 · 50 ejercicios
A2: 20 rápidos con los datos y flujos cargados y 30 completos con solo la consigna, para armar el flujo de fondos desde cero. Cada respuesta se corrige sola.
A3: Hojas: Rápidos · Completos · Soluciones (al final, para mirar después).
A5: N.º | B5: Tipo | C5: Tema | D5: Estado | E5: Ir
A6: 51 | B6: Rápido | C6: Cupón cero · precio | D6: =IF(Rápidos!$D$10="","Pendiente",Rápidos!$D$10) | E6: Ir al ej. 51
A7: 52 | B7: Rápido | C7: Letra · TNA | D7: =IF(Rápidos!$D$18="","Pendiente",Rápidos!$D$18) | E7: Ir al ej. 52
A8: 53 | B8: Rápido | C8: TNA → TEA | D8: =IF(Rápidos!$D$25="","Pendiente",Rápidos!$D$25) | E8: Ir al ej. 53
A9: 54 | B9: Rápido | C9: TEA → TEM | D9: =IF(Rápidos!$D$32="","Pendiente",Rápidos!$D$32) | E9: Ir al ej. 54
A10: 55 | B10: Rápido | C10: Bullet anual · TIR | D10: =IF(Rápidos!$D$39="","Pendiente",Rápidos!$D$39) | E10: Ir al ej. 55
A11: 56 | B11: Rápido | C11: Semestral · TIR → TEA | D11: =IF(Rápidos!$D$46="","Pendiente",Rápidos!$D$46) | E11: Ir al ej. 56
A12: 57 | B12: Rápido | C12: Current yield | D12: =IF(Rápidos!$D$53="","Pendiente",Rápidos!$D$53) | E12: Ir al ej. 57
A13: 58 | B13: Rápido | C13: Paridad | D13: =IF(Rápidos!$D$61="","Pendiente",Rápidos!$D$61) | E13: Ir al ej. 58
A14: 59 | B14: Rápido | C14: Valor técnico | D14: =IF(Rápidos!$D$69="","Pendiente",Rápidos!$D$69) | E14: Ir al ej. 59
A15: 60 | B15: Rápido | C15: Duration con flujos | D15: =IF(Rápidos!$D$77="","Pendiente",Rápidos!$D$77) | E15: Ir al ej. 60
A16: 61 | B16: Rápido | C16: Duration modificada | D16: =IF(Rápidos!$D$85="","Pendiente",Rápidos!$D$85) | E16: Ir al ej. 61
A17: 62 | B17: Rápido | C17: Variación de precio con DM | D17: =IF(Rápidos!$D$92="","Pendiente",Rápidos!$D$92) | E17: Ir al ej. 62
A18: 63 | B18: Rápido | C18: DM + convexidad | D18: =IF(Rápidos!$D$100="","Pendiente",Rápidos!$D$100) | E18: Ir al ej. 63
A19: 64 | B19: Rápido | C19: Precio con flujos | D19: =IF(Rápidos!$D$108="","Pendiente",Rápidos!$D$108) | E19: Ir al ej. 64
A20: 65 | B20: Rápido | C20: PPV con flujos | D20: =IF(Rápidos!$D$115="","Pendiente",Rápidos!$D$115) | E20: Ir al ej. 65
A21: 66 | B21: Rápido | C21: Duration de cartera | D21: =IF(Rápidos!$D$126="","Pendiente",Rápidos!$D$126) | E21: Ir al ej. 66
A22: 67 | B22: Rápido | C22: TIR.NO.PER | D22: =IF(Rápidos!$D$133="","Pendiente",Rápidos!$D$133) | E22: Ir al ej. 67
A23: 68 | B23: Rápido | C23: Monto a invertir | D23: =IF(Rápidos!$D$141="","Pendiente",Rápidos!$D$141) | E23: Ir al ej. 68
A24: 69 | B24: Rápido | C24: Caución | D24: =IF(Rápidos!$D$149="","Pendiente",Rápidos!$D$149) | E24: Ir al ej. 69
A25: 70 | B25: Rápido | C25: TIR nominal → TEA | D25: =IF(Rápidos!$D$156="","Pendiente",Rápidos!$D$156) | E25: Ir al ej. 70
A26: 71 | B26: Completo | C26: Bullet anual · TIR | D26: =IF(Completos!$D$7="","Pendiente",Completos!$D$7) | E26: Ir al ej. 71
A27: 72 | B27: Completo | C27: Bullet semestral · TEA | D27: =IF(Completos!$D$28="","Pendiente",Completos!$D$28) | E27: Ir al ej. 72
A28: 73 | B28: Completo | C28: Bullet semestral · TIR nominal | D28: =IF(Completos!$D$49="","Pendiente",Completos!$D$49) | E28: Ir al ej. 73
A29: 74 | B29: Completo | C29: Amortizable · precio | D29: =IF(Completos!$D$70="","Pendiente",Completos!$D$70) | E29: Ir al ej. 74
A30: 75 | B30: Completo | C30: Amortizable con gracia · TEA | D30: =IF(Completos!$D$91="","Pendiente",Completos!$D$91) | E30: Ir al ej. 75
A31: 76 | B31: Completo | C31: Duration de un bullet | D31: =IF(Completos!$D$112="","Pendiente",Completos!$D$112) | E31: Ir al ej. 76
A32: 77 | B32: Completo | C32: Duration modificada semestral | D32: =IF(Completos!$D$133="","Pendiente",Completos!$D$133) | E32: Ir al ej. 77
A33: 78 | B33: Completo | C33: Convexidad | D33: =IF(Completos!$D$154="","Pendiente",Completos!$D$154) | E33: Ir al ej. 78
A34: 79 | B34: Completo | C34: PPV de un amortizable | D34: =IF(Completos!$D$175="","Pendiente",Completos!$D$175) | E34: Ir al ej. 79
A35: 80 | B35: Completo | C35: Sensibilidad por duration | D35: =IF(Completos!$D$196="","Pendiente",Completos!$D$196) | E35: Ir al ej. 80
A36: 81 | B36: Completo | C36: Sensibilidad con convexidad | D36: =IF(Completos!$D$217="","Pendiente",Completos!$D$217) | E36: Ir al ej. 81
A37: 82 | B37: Completo | C37: Variación real de precio | D37: =IF(Completos!$D$238="","Pendiente",Completos!$D$238) | E37: Ir al ej. 82
A38: 83 | B38: Completo | C38: AL30 · TIR | D38: =IF(Completos!$D$259="","Pendiente",Completos!$D$259) | E38: Ir al ej. 83
A39: 84 | B39: Completo | C39: GD35 · TIR | D39: =IF(Completos!$D$280="","Pendiente",Completos!$D$280) | E39: Ir al ej. 84
A40: 85 | B40: Completo | C40: Precio con fechas | D40: =IF(Completos!$D$301="","Pendiente",Completos!$D$301) | E40: Ir al ej. 85
A41: 86 | B41: Completo | C41: Duration con fechas | D41: =IF(Completos!$D$322="","Pendiente",Completos!$D$322) | E41: Ir al ej. 86
A42: 87 | B42: Completo | C42: Letra · TEM | D42: =IF(Completos!$D$343="","Pendiente",Completos!$D$343) | E42: Ir al ej. 87
A43: 88 | B43: Completo | C43: ON trimestral amortizable · TEA | D43: =IF(Completos!$D$364="","Pendiente",Completos!$D$364) | E43: Ir al ej. 88
A44: 89 | B44: Completo | C44: Paridad de un amortizable | D44: =IF(Completos!$D$385="","Pendiente",Completos!$D$385) | E44: Ir al ej. 89
A45: 90 | B45: Completo | C45: Monto con comisiones | D45: =IF(Completos!$D$406="","Pendiente",Completos!$D$406) | E45: Ir al ej. 90
A46: 91 | B46: Completo | C46: Duration de cartera | D46: =IF(Completos!$D$427="","Pendiente",Completos!$D$427) | E46: Ir al ej. 91
A47: 92 | B47: Completo | C47: Step-up · TIR | D47: =IF(Completos!$D$448="","Pendiente",Completos!$D$448) | E47: Ir al ej. 92
A48: 93 | B48: Completo | C48: DM de un amortizable | D48: =IF(Completos!$D$469="","Pendiente",Completos!$D$469) | E48: Ir al ej. 93
A49: 94 | B49: Completo | C49: Amortizable · precio para una TIR | D49: =IF(Completos!$D$490="","Pendiente",Completos!$D$490) | E49: Ir al ej. 94
A50: 95 | B50: Completo | C50: Error de la duration | D50: =IF(Completos!$D$511="","Pendiente",Completos!$D$511) | E50: Ir al ej. 95
A51: 96 | B51: Completo | C51: TIR entre fechas de pago | D51: =IF(Completos!$D$532="","Pendiente",Completos!$D$532) | E51: Ir al ej. 96
A52: 97 | B52: Completo | C52: TIR con precio limpio | D52: =IF(Completos!$D$553="","Pendiente",Completos!$D$553) | E52: Ir al ej. 97
A53: 98 | B53: Completo | C53: AL30 · duration | D53: =IF(Completos!$D$574="","Pendiente",Completos!$D$574) | E53: Ir al ej. 98
A54: 99 | B54: Completo | C54: AE38 · PPV | D54: =IF(Completos!$D$595="","Pendiente",Completos!$D$595) | E54: Ir al ej. 99
A55: 100 | B55: Completo | C55: GD41 · precio | D55: =IF(Completos!$D$616="","Pendiente",Completos!$D$616) | E55: Ir al ej. 100
C57: Correctos | D57: =COUNTIF(D6:D55,"✔*")
C58: Respondidos | D58: =COUNTIF(D6:D55,"✔*")+COUNTIF(D6:D55,"✘*")

Sheet Rápidos
A1: Ejercicios rápidos (51 a 70)
A2: Los datos y los flujos ya están cargados en azul. Resolvelos con fórmulas en la celda amarilla o en el espacio de al lado.
A3: Cómo cargar la respuesta: tasas y variaciones como porcentaje (7,72%), precios, durations y montos como número (92,42).
A5: Ejercicio 51 | B5: Cupón cero · precio
A6: Un bono cupón cero de VN 100 vence dentro de 3 años. La TIR efectiva anual de mercado es 11%. ¿Cuál es su precio?
A7: Valor nominal | B7: 100
A8: Años al vencimiento | B8: 3
A9: TIR efectiva anual | B9: 0.11
A10: Tu respuesta | D10: =IF(B10="","",IF(ABS(B10-Soluciones!$C$5)<=MAX(0.003*ABS(Soluciones!$C$5),0.0001),"✔ Correcto","✘ Revisá"))
A13: Ejercicio 52 | B13: Letra · TNA
A14: Una letra que paga 100 al vencimiento, dentro de 75 días, cotiza a 95,80. ¿Qué TNA (interés simple, base 365) rinde?
A15: Precio | B15: 95.8
A16: Valor al vencimiento | B16: 100
A17: Días | B17: 75
A18: Tu respuesta | D18: =IF(B18="","",IF(ABS(B18-Soluciones!$C$11)<=MAX(0.003*ABS(Soluciones!$C$11),0.0001),"✔ Correcto","✘ Revisá"))
A21: Ejercicio 53 | B21: TNA → TEA
A22: Un plazo fijo paga una TNA de 36% con capitalización cada 30 días. ¿Cuál es la TEA si renovás capital e intereses todo el año?
A23: TNA | B23: 0.36
A24: Días del período | B24: 30
A25: Tu respuesta | D25: =IF(B25="","",IF(ABS(B25-Soluciones!$C$17)<=MAX(0.003*ABS(Soluciones!$C$17),0.0001),"✔ Correcto","✘ Revisá"))
A28: Ejercicio 54 | B28: TEA → TEM
A29: Una inversión rinde una TEA de 45%. ¿Cuál es la tasa efectiva equivalente para 30 días?
A30: TEA | B30: 0.45
A31: Días | B31: 30
A32: Tu respuesta | D32: =IF(B32="","",IF(ABS(B32-Soluciones!$C$23)<=MAX(0.003*ABS(Soluciones!$C$23),0.0001),"✔ Correcto","✘ Revisá"))
A35: Ejercicio 55 | B35: Bullet anual · TIR
A36: Pagás 92 por un bono que te paga 6 por año durante 4 años y devuelve 100 con el último cupón. ¿Cuál es la TIR efectiva anual?
A37: Año | B37: 0 | C37: 1 | D37: 2 | E37: 3 | F37: 4
A38: Flujo | B38: -92 | C38: 6 | D38: 6 | E38: 6 | F38: 106
A39: Tu respuesta | D39: =IF(B39="","",IF(ABS(B39-Soluciones!$C$29)<=MAX(0.003*ABS(Soluciones!$C$29),0.0001),"✔ Correcto","✘ Revisá"))
A42: Ejercicio 56 | B42: Semestral · TIR → TEA
A43: Un bono paga 4 por semestre durante 3 semestres y 104 en el cuarto. Cotiza 97. ¿Cuál es su TIR efectiva anual?
A44: Año | B44: 0 | C44: 1 | D44: 2 | E44: 3 | F44: 4
A45: Flujo | B45: -97 | C45: 4 | D45: 4 | E45: 4 | F45: 104
A46: Tu respuesta | D46: =IF(B46="","",IF(ABS(B46-Soluciones!$C$35)<=MAX(0.003*ABS(Soluciones!$C$35),0.0001),"✔ Correcto","✘ Revisá"))
A49: Ejercicio 57 | B49: Current yield
A50: Un bono paga un cupón anual de 7,5% sobre VN 100 y cotiza a 88. ¿Cuál es su current yield?
A51: Cupón anual (por 100 VN) | B51: 7.5
A52: Precio | B52: 88
A53: Tu respuesta | D53: =IF(B53="","",IF(ABS(B53-Soluciones!$C$41)<=MAX(0.003*ABS(Soluciones!$C$41),0.0001),"✔ Correcto","✘ Revisá"))
A56: Ejercicio 58 | B56: Paridad
A57: Un bono tiene valor residual 60 e intereses corridos 1,20 por cada 100 de VN original. Cotiza 55,40. ¿Cuál es su paridad?
A58: Valor residual | B58: 60
A59: Intereses corridos | B59: 1.2
A60: Precio | B60: 55.4
A61: Tu respuesta | D61: =IF(B61="","",IF(ABS(B61-Soluciones!$C$47)<=MAX(0.003*ABS(Soluciones!$C$47),0.0001),"✔ Correcto","✘ Revisá"))
A64: Ejercicio 59 | B64: Valor técnico
A65: Un bono con valor residual 80 paga cupón de 6% anual sobre saldo. Pasaron 73 días desde el último pago. ¿Cuál es su valor técnico (intereses corridos en base actual/365)?
A66: Valor residual | B66: 80
A67: Cupón anual | B67: 0.06
A68: Días corridos | B68: 73
A69: Tu respuesta | D69: =IF(B69="","",IF(ABS(B69-Soluciones!$C$53)<=MAX(0.003*ABS(Soluciones!$C$53),0.0001),"✔ Correcto","✘ Revisá"))
A72: Ejercicio 60 | B72: Duration con flujos
A73: Un bono paga 8, 8, 8 y 108 al final de los años 1 a 4. Con una TIR efectiva anual de 10%, ¿cuál es su duration (Macaulay, en años)?
A74: TIR efectiva anual | B74: 0.1
A75: Año | B75: 1 | C75: 2 | D75: 3 | E75: 4
A76: Flujo | B76: 8 | C76: 8 | D76: 8 | E76: 108
A77: Tu respuesta | D77: =IF(B77="","",IF(ABS(B77-Soluciones!$C$59)<=MAX(0.003*ABS(Soluciones!$C$59),0.0001),"✔ Correcto","✘ Revisá"))
A80: Ejercicio 61 | B80: Duration modificada
A81: Un bono tiene una duration de 4,35 años y una TIR de 9% nominal anual capitalizable semestralmente. ¿Cuál es su duration modificada?
A82: Duration | B82: 4.35
A83: TIR nominal anual | B83: 0.09
A84: Pagos por año (m) | B84: 2
A85: Tu respuesta | D85: =IF(B85="","",IF(ABS(B85-Soluciones!$C$65)<=MAX(0.003*ABS(Soluciones!$C$65),0.0001),"✔ Correcto","✘ Revisá"))
A88: Ejercicio 62 | B88: Variación de precio con DM
A89: Un bono tiene duration modificada 5,2. Si su TIR sube 120 puntos básicos, ¿cuánto varía su precio (aproximación por duration)?
A90: Duration modificada | B90: 5.2
A91: Cambio de TIR (decimal) | B91: 0.012
A92: Tu respuesta | D92: =IF(B92="","",IF(ABS(B92-Soluciones!$C$71)<=MAX(0.003*ABS(Soluciones!$C$71),0.0001),"✔ Correcto","✘ Revisá"))
A95: Ejercicio 63 | B95: DM + convexidad
A96: Un bono tiene duration modificada 7,1 y convexidad 62. Si su TIR baja 150 puntos básicos, ¿cuánto varía su precio usando duration y convexidad?
A97: Duration modificada | B97: 7.1
A98: Convexidad | B98: 62
A99: Cambio de TIR (decimal) | B99: -0.015
A100: Tu respuesta | D100: =IF(B100="","",IF(ABS(B100-Soluciones!$C$77)<=MAX(0.003*ABS(Soluciones!$C$77),0.0001),"✔ Correcto","✘ Revisá"))
A103: Ejercicio 64 | B103: Precio con flujos
A104: Un bono paga 10 al final de los años 1 a 4 y 110 en el año 5. Con una TIR efectiva anual de 12%, ¿cuánto vale?
A105: TIR efectiva anual | B105: 0.12
A106: Año | B106: 1 | C106: 2 | D106: 3 | E106: 4 | F106: 5
A107: Flujo | B107: 10 | C107: 10 | D107: 10 | E107: 10 | F107: 110
A108: Tu respuesta | D108: =IF(B108="","",IF(ABS(B108-Soluciones!$C$83)<=MAX(0.003*ABS(Soluciones!$C$83),0.0001),"✔ Correcto","✘ Revisá"))
A111: Ejercicio 65 | B111: PPV con flujos
A112: Un bono amortiza 25 por año y paga intereses sobre saldo: los flujos de los años 1 a 4 son 33, 31, 29 y 27. ¿Cuál es su promedio ponderado de vida (PPV) según la fórmula Σ t·(A+R) / Σ (A+R)?
A113: Año | B113: 1 | C113: 2 | D113: 3 | E113: 4
A114: Flujo | B114: 33 | C114: 31 | D114: 29 | E114: 27
A115: Tu respuesta | D115: =IF(B115="","",IF(ABS(B115-Soluciones!$C$89)<=MAX(0.003*ABS(Soluciones!$C$89),0.0001),"✔ Correcto","✘ Revisá"))
A118: Ejercicio 66 | B118: Duration de cartera
A119: Una cartera tiene 40% en un bono de duration 2,1; 35% en uno de duration 4,8 y 25% en uno de duration 7,3. ¿Cuál es la duration de la cartera?
A120: Peso A | B120: 0.4
A121: Duration A | B121: 2.1
A122: Peso B | B122: 0.35
A123: Duration B | B123: 4.8
A124: Peso C | B124: 0.25
A125: Duration C | B125: 7.3
A126: Tu respuesta | D126: =IF(B126="","",IF(ABS(B126-Soluciones!$C$95)<=MAX(0.003*ABS(Soluciones!$C$95),0.0001),"✔ Correcto","✘ Revisá"))
A129: Ejercicio 67 | B129: TIR.NO.PER
A130: Comprás un bono el 15/01/2027 a 95 y cobrás 3 el 15/07/2027, 3 el 15/01/2028 y 103 el 15/07/2028. ¿Cuál es la TIR efectiva anual (TIR.NO.PER)?
A131: Fecha | B131: 46402 | C131: 46583 | D131: 46767 | E131: 46949
A132: Flujo | B132: -95 | C132: 3 | D132: 3 | E132: 103
A133: Tu respuesta | D133: =IF(B133="","",IF(ABS(B133-Soluciones!$C$101)<=MAX(0.003*ABS(Soluciones!$C$101),0.0001),"✔ Correcto","✘ Revisá"))
...

Sheet Completos
A1: Ejercicios completos (71 a 100)
A2: Solo la consigna. Armá vos el flujo de fondos en el espacio de abajo de cada uno y calculá lo que se pide.
A3: Cómo cargar la respuesta: tasas y variaciones como porcentaje (7,72%), precios, durations y montos como número (92,42).
A5: Ejercicio 71 | B5: Bullet anual · TIR
A6: Un bono de VN 100 vence dentro de 4 años, paga un cupón de 7% anual al final de cada año y devuelve todo el capital al vencimiento. Cotiza a 96,50. Calculá su TIR efectiva anual.
A7: Tu respuesta | D7: =IF(B7="","",IF(ABS(B7-Soluciones!$C$125)<=MAX(0.003*ABS(Soluciones!$C$125),0.0001),"✔ Correcto","✘ Revisá"))
A8: Tu espacio de trabajo
A26: Ejercicio 72 | B26: Bullet semestral · TEA
A27: Una obligación negociable de VN 100 vence dentro de 3 años, paga un cupón de 9% nominal anual en pagos semestrales y amortiza todo al vencimiento. Cotiza a 101,20. Calculá su TIR efectiva anual.
A28: Tu respuesta | D28: =IF(B28="","",IF(ABS(B28-Soluciones!$C$145)<=MAX(0.003*ABS(Soluciones!$C$145),0.0001),"✔ Correcto","✘ Revisá"))
A29: Tu espacio de trabajo
A47: Ejercicio 73 | B47: Bullet semestral · TIR nominal
A48: Un bono de VN 100 vence dentro de 5 años, paga un cupón de 6% nominal anual en pagos semestrales y amortiza todo al vencimiento. Cotiza a 94. Calculá su TIR expresada como tasa nominal anual capitalizable semestralmente.
A49: Tu respuesta | D49: =IF(B49="","",IF(ABS(B49-Soluciones!$C$167)<=MAX(0.003*ABS(Soluciones!$C$167),0.0001),"✔ Correcto","✘ Revisá"))
A50: Tu espacio de trabajo
A68: Ejercicio 74 | B68: Amortizable · precio
A69: Un bono de VN 100 amortiza 25% del capital al final de cada uno de los próximos 4 años y paga un cupón de 8% anual sobre el saldo pendiente al inicio de cada año. ¿Cuánto vale si la TIR efectiva anual de mercado es 10%?
A70: Tu respuesta | D70: =IF(B70="","",IF(ABS(B70-Soluciones!$C$193)<=MAX(0.003*ABS(Soluciones!$C$193),0.0001),"✔ Correcto","✘ Revisá"))
A71: Tu espacio de trabajo
A89: Ejercicio 75 | B89: Amortizable con gracia · TEA
A90: Un bono de VN 100 vence dentro de 5 años. Paga cupón de 5% nominal anual en pagos semestrales sobre el saldo. Amortiza en 5 cuotas semestrales iguales, la primera a los 3 años (semestre 6) y la última al vencimiento. Cotiza a 88. Calculá su TIR efectiva anual.
A91: Tu respuesta | D91: =IF(B91="","",IF(ABS(B91-Soluciones!$C$213)<=MAX(0.003*ABS(Soluciones!$C$213),0.0001),"✔ Correcto","✘ Revisá"))
A92: Tu espacio de trabajo
A110: Ejercicio 76 | B110: Duration de un bullet
A111: Un bono de VN 100 vence dentro de 5 años, paga un cupón de 6% anual al final de cada año y amortiza todo al vencimiento. Con una TIR efectiva anual de 8%, calculá su duration (Macaulay, en años).
A112: Tu respuesta | D112: =IF(B112="","",IF(ABS(B112-Soluciones!$C$239)<=MAX(0.003*ABS(Soluciones!$C$239),0.0001),"✔ Correcto","✘ Revisá"))
A113: Tu espacio de trabajo
A131: Ejercicio 77 | B131: Duration modificada semestral
A132: Un bono de VN 100 vence dentro de 3 años, paga un cupón de 10% nominal anual en pagos semestrales y amortiza todo al vencimiento. Su TIR es 12% nominal anual capitalizable semestralmente. Calculá su duration modificada.
A133: Tu respuesta | D133: =IF(B133="","",IF(ABS(B133-Soluciones!$C$260)<=MAX(0.003*ABS(Soluciones!$C$260),0.0001),"✔ Correcto","✘ Revisá"))
A134: Tu espacio de trabajo
A152: Ejercicio 78 | B152: Convexidad
A153: Un bono de VN 100 vence dentro de 4 años, paga un cupón de 5% anual al final de cada año y amortiza todo al vencimiento. Con una TIR efectiva anual de 9%, calculá su convexidad.
A154: Tu respuesta | D154: =IF(B154="","",IF(ABS(B154-Soluciones!$C$282)<=MAX(0.003*ABS(Soluciones!$C$282),0.0001),"✔ Correcto","✘ Revisá"))
A155: Tu espacio de trabajo
A173: Ejercicio 79 | B173: PPV de un amortizable
A174: Un bono de VN 100 vence dentro de 6 años, paga un cupón de 6% anual sobre saldo al final de cada año y amortiza en 3 cuotas anuales iguales en los años 4, 5 y 6. Calculá su promedio ponderado de vida (PPV) según la fórmula del apunte.
A175: Tu respuesta | D175: =IF(B175="","",IF(ABS(B175-Soluciones!$C$302)<=MAX(0.003*ABS(Soluciones!$C$302),0.0001),"✔ Correcto","✘ Revisá"))
A176: Tu espacio de trabajo
A194: Ejercicio 80 | B194: Sensibilidad por duration
A195: Un bono de VN 100 vence dentro de 6 años, paga un cupón de 7% anual al final de cada año y amortiza todo al vencimiento. Hoy su TIR efectiva anual es 9%. Si la TIR sube a 10,5%, ¿cuánto varía su precio según la aproximación por duration modificada?
A196: Tu respuesta | D196: =IF(B196="","",IF(ABS(B196-Soluciones!$C$324)<=MAX(0.003*ABS(Soluciones!$C$324),0.0001),"✔ Correcto","✘ Revisá"))
A197: Tu espacio de trabajo
A215: Ejercicio 81 | B215: Sensibilidad con convexidad
A216: Un bono de VN 100 vence dentro de 8 años, paga un cupón de 4% anual al final de cada año y amortiza todo al vencimiento. Hoy su TIR efectiva anual es 7%. Si la TIR baja a 5%, ¿cuánto varía su precio según la aproximación por duration modificada y convexidad?
A217: Tu respuesta | D217: =IF(B217="","",IF(ABS(B217-Soluciones!$C$346)<=MAX(0.003*ABS(Soluciones!$C$346),0.0001),"✔ Correcto","✘ Revisá"))
A218: Tu espacio de trabajo
A236: Ejercicio 82 | B236: Variación real de precio
A237: Un bono cupón cero de VN 100 vence dentro de 7 años. Su TIR efectiva anual pasa de 9% a 11%. ¿Cuál es la variación porcentual real de su precio?
A238: Tu respuesta | D238: =IF(B238="","",IF(ABS(B238-Soluciones!$C$370)<=MAX(0.003*ABS(Soluciones!$C$370),0.0001),"✔ Correcto","✘ Revisá"))
A239: Tu espacio de trabajo
A257: Ejercicio 83 | B257: AL30 · TIR
A258: El AL30 amortiza 4% de su VN original el 09/07/2024 y 8% en cada fecha de pago siguiente (9 de enero y 9 de julio) hasta el 09/07/2030. Paga cupón semestral sobre el saldo, a una tasa de 0,75% anual hasta el pago del 09/07/2027 inclusive y de 1,75% anual desde ahí (cada cupón = tasa anual / 2 × saldo al inicio del semestre). El 09/01/2027, ya cobrado el pago de ese día, lo comprás a 49,50 por cada 100 de VN original. Calculá la TIR efectiva anual (TIR.NO.PER).
A259: Tu respuesta | D259: =IF(B259="","",IF(ABS(B259-Soluciones!$C$393)<=MAX(0.003*ABS(Soluciones!$C$393),0.0001),"✔ Correcto","✘ Revisá"))
A260: Tu espacio de trabajo
A278: Ejercicio 84 | B278: GD35 · TIR
A279: El GD35 paga cupón semestral (9 de enero y 9 de julio) sobre el saldo, a una tasa de 5% anual desde el 09/07/2028 (cada cupón = tasa anual / 2 × saldo al inicio del semestre). Amortiza en 10 cuotas semestrales iguales, la primera el 09/01/2031 y la última el 09/07/2035. El 09/07/2028, ya cobrado el pago de ese día, cotiza a 70 por cada 100 de VN. Calculá la TIR efectiva anual (TIR.NO.PER).
A280: Tu respuesta | D280: =IF(B280="","",IF(ABS(B280-Soluciones!$C$416)<=MAX(0.003*ABS(Soluciones!$C$416),0.0001),"✔ Correcto","✘ Revisá"))
A281: Tu espacio de trabajo
A299: Ejercicio 85 | B299: Precio con fechas
A300: Una obligación negociable de VN 100 paga un cupón de 8% nominal anual en pagos trimestrales iguales sobre el VN (15 de marzo, junio, septiembre y diciembre) y amortiza todo el 15/03/2028. El 15/12/2026, ya cobrado el cupón de ese día, ¿cuánto vale si la TIR efectiva anual de mercado es 11%? (Descontá con días/365.)
A301: Tu respuesta | D301: =IF(B301="","",IF(ABS(B301-Soluciones!$C$446)<=MAX(0.003*ABS(Soluciones!$C$446),0.0001),"✔ Correcto","✘ Revisá"))
A302: Tu espacio de trabajo
A320: Ejercicio 86 | B320: Duration con fechas
A321: Un bono de VN 100 paga un cupón de 6% nominal anual en pagos semestrales iguales sobre el VN (1 de junio y 1 de diciembre) y amortiza todo el 01/12/2029. El 01/12/2026, ya cobrado el cupón de ese día, su TIR efectiva anual es 9%. Calculá su duration en años (días/365).
A322: Tu respuesta | D322: =IF(B322="","",IF(ABS(B322-Soluciones!$C$467)<=MAX(0.003*ABS(Soluciones!$C$467),0.0001),"✔ Correcto","✘ Revisá"))
A323: Tu espacio de trabajo
A341: Ejercicio 87 | B341: Letra · TEM
A342: Comprás una letra a 104,10 que paga 112,40 al vencimiento, dentro de 120 días. ¿Cuál es su tasa efectiva mensual (30 días)?
A343: Tu respuesta | D343: =IF(B343="","",IF(ABS(B343-Soluciones!$C$489)<=MAX(0.003*ABS(Soluciones!$C$489),0.0001),"✔ Correcto","✘ Revisá"))
A344: Tu espacio de trabajo
A362: Ejercicio 88 | B362: ON trimestral amortizable · TEA
A363: Una obligación negociable en dólares de VN 100 paga un cupón de 7% nominal anual en pagos trimestrales sobre el saldo. Amortiza 50% a los 2 años y el 50% restante a los 3 años, junto con el cupón de esas fechas. Cotiza a 99,30. Calculá su TIR efectiva anual.
A364: Tu respuesta | D364: =IF(B364="","",IF(ABS(B364-Soluciones!$C$506)<=MAX(0.003*ABS(Soluciones!$C$506),0.0001),"✔ Correcto","✘ Revisá"))
A365: Tu espacio de trabajo
A383: Ejercicio 89 | B383: Paridad de un amortizable
A384: Una obligación negociable de VN original 100 ya amortizó el 40% de su capital. Paga cupón de 9% anual sobre el saldo, y pasaron 90 días desde el último pago de intereses (intereses corridos en base actual/365). Cotiza a 58,30 por cada 100 de VN original. Calculá su paridad.
A385: Tu respuesta | D385: =IF(B385="","",IF(ABS(B385-Soluciones!$C$534)<=MAX(0.003*ABS(Soluciones!$C$534),0.0001),"✔ Correcto","✘ Revisá"))
A386: Tu espacio de trabajo
A404: Ejercicio 90 | B404: Monto con comisiones
A405: Vas a comprar VN 15.000 de un bono que cotiza a 84,75 por cada 100 de VN. Pagás una comisión de 0,5% y derechos de mercado de 0,01%, ambos sobre el monto bruto. ¿Cuánto pagás en total?
A406: Tu respuesta | D406: =IF(B406="","",IF(ABS(B406-Soluciones!$C$540)<=MAX(0.003*ABS(Soluciones!$C$540),0.0001),"✔ Correcto","✘ Revisá"))
A407: Tu espacio de trabajo
A425: Ejercicio 91 | B425: Duration de cartera
A426: Tu cartera tiene 30% en un bono cupón cero que vence en 2 años, 30% en un bono bullet a 3 años con cupón de 8% anual y 40% en un bono bullet a 5 años con cupón de 6% anual. Todos rinden una TIR efectiva anual de 10% y pagan al final de cada año. Calculá la duration de la cartera.
A427: Tu respuesta | D427: =IF(B427="","",IF(ABS(B427-Soluciones!$C$546)<=MAX(0.003*ABS(Soluciones!$C$546),0.0001),"✔ Correcto","✘ Revisá"))
A428: Tu espacio de trabajo
A446: Ejercicio 92 | B446: Step-up · TIR
A447: Un bono de VN 100 vence dentro de 4 años y amortiza todo al vencimiento. Paga cupón anual de 2% en los años 1 y 2 y de 5% en los años 3 y 4. Cotiza a 90. Calculá su TIR efectiva anual.
A448: Tu respuesta | D448: =IF(B448="","",IF(ABS(B448-Soluciones!$C$562)<=MAX(0.003*ABS(Soluciones!$C$562),0.0001),"✔ Correcto","✘ Revisá"))
A449: Tu espacio de trabajo
A467: Ejercicio 93 | B467: DM de un amortizable
A468: Un bono de VN 100 amortiza 50% a los 3 años y 50% a los 5 años. Paga un cupón de 6% anual sobre el saldo al final de cada año. Con una TIR efectiva anual de 8%, calculá su duration modificada (DM = D / (1 + TIR)).
A469: Tu respuesta | D469: =IF(B469="","",IF(ABS(B469-Soluciones!$C$582)<=MAX(0.003*ABS(Soluciones!$C$582),0.0001),"✔ Correcto","✘ Revisá"))
A470: Tu espacio de trabajo
A488: Ejercicio 94 | B488: Amortizable · precio para una TIR
A489: Un bono de VN 100 vence dentro de 5 años, paga un cupón de 10% nominal anual en pagos semestrales sobre el saldo y amortiza en 10 cuotas semestrales iguales desde el primer semestre. ¿Qué precio tiene que pagar el mercado para que la TIR sea 14% nominal anual capitalizable semestralmente?
A490: Tu respuesta | D490: =IF(B490="","",IF(ABS(B490-Soluciones!$C$603)<=MAX(0.003*ABS(Soluciones!$C$603),0.0001),"✔ Correcto","✘ Revisá"))
A491: Tu espacio de trabajo
A509: Ejercicio 95 | B509: Error de la duration
...

Sheet Soluciones
A1: Soluciones · serie 2
A2: Mirala después de resolver. En los completos está el flujo de fondos armado, con fórmulas vivas.
A4: Ejercicio 51 | B4: Rápido · Cupón cero · precio
A5: Respuesta | C5: 73.119138 | D5: 73,12
A6: En Excel | C6: =100/(1+11%)^3 ó =VA(11%;3;0;-100)
A7: Explicación | C7: El único flujo (100) se descuenta 3 años a la TIR: P = 100 / 1,11³.
A10: Ejercicio 52 | B10: Rápido · Letra · TNA
A11: Respuesta | C11: 0.21336117 | D11: 21,34 %
A12: En Excel | C12: =(100/95,8-1)*365/75
A13: Explicación | C13: Rendimiento directo del plazo (100/95,80 − 1) llevado a año en forma proporcional: × 365/75.
A16: Ejercicio 53 | B16: Rápido · TNA → TEA
A17: Respuesta | C17: 0.4258623 | D17: 42,59 %
A18: En Excel | C18: =(1+36%*30/365)^(365/30)-1
A19: Explicación | C19: Tasa del período = TNA × 30/365; se capitaliza 365/30 veces en el año.
A22: Ejercicio 54 | B22: Rápido · TEA → TEM
A23: Respuesta | C23: 0.031010584 | D23: 3,10 %
A24: En Excel | C24: =(1+45%)^(30/365)-1
A25: Explicación | C25: Las tasas efectivas se convierten con potencias: (1 + TEA)^(30/365) − 1.
A28: Ejercicio 55 | B28: Rápido · Bullet anual · TIR
A29: Respuesta | C29: 0.084390116 | D29: 8,44 %
A30: En Excel | C30: =TIR(flujos)
A31: Explicación | C31: Con pagos anuales, la TIR de los flujos ya es efectiva anual.
A34: Ejercicio 56 | B34: Rápido · Semestral · TIR → TEA
A35: Respuesta | C35: 0.099204442 | D35: 9,92 %
A36: En Excel | C36: =(1+TIR(flujos))^2-1
A37: Explicación | C37: TIR(flujos) da la tasa semestral; se pasa a efectiva anual elevando al cuadrado.
A40: Ejercicio 57 | B40: Rápido · Current yield
A41: Respuesta | C41: 0.085227273 | D41: 8,52 %
A42: En Excel | C42: =7,5/88
A43: Explicación | C43: CY = renta anual / precio.
A46: Ejercicio 58 | B46: Rápido · Paridad
A47: Respuesta | C47: 0.90522876 | D47: 90,52 %
A48: En Excel | C48: =55,4/(60+1,2)
A49: Explicación | C49: Paridad = precio / valor técnico, con VT = VR + intereses corridos.
A52: Ejercicio 59 | B52: Rápido · Valor técnico
A53: Respuesta | C53: 80.96 | D53: 80,96
A54: En Excel | C54: =80+80*6%*73/365
A55: Explicación | C55: VT = VR + VR × cupón × días/365.
A58: Ejercicio 60 | B58: Rápido · Duration con flujos
A59: Respuesta | C59: 3.5616942 | D59: 3,562
A60: En Excel | C60: =SUMAPRODUCTO(t;flujo/(1+10%)^t)/SUMAPRODUCTO(flujo/(1+10%)^t)
A61: Explicación | C61: D = Σ t · VA / Σ VA: el promedio de los plazos ponderado por el valor actual de cada flujo.
A64: Ejercicio 61 | B64: Rápido · Duration modificada
A65: Respuesta | C65: 4.1626794 | D65: 4,163
A66: En Excel | C66: =4,35/(1+9%/2)
A67: Explicación | C67: DM = D / (1 + TIR/m).
A70: Ejercicio 62 | B70: Rápido · Variación de precio con DM
A71: Respuesta | C71: -0.0624 | D71: -6,24 %
A72: En Excel | C72: =-5,2*1,2%
A73: Explicación | C73: Var.% Pr. ≈ − DM × ΔTIR. 120 pb = 0,012.
A76: Ejercicio 63 | B76: Rápido · DM + convexidad
A77: Respuesta | C77: 0.113475 | D77: 11,35 %
A78: En Excel | C78: =-7,1*(-1,5%)+0,5*62*(-1,5%)^2
A79: Explicación | C79: Var.% Pr. ≈ − DM × ΔTIR + ½ × C × ΔTIR². El término de convexidad siempre suma.
A82: Ejercicio 64 | B82: Rápido · Precio con flujos
A83: Respuesta | C83: 92.790448 | D83: 92,79
A84: En Excel | C84: =VNA(12%;flujos)
A85: Explicación | C85: El precio es la suma de los flujos descontados a la TIR.
A88: Ejercicio 65 | B88: Rápido · PPV con flujos
A89: Respuesta | C89: 2.4166667 | D89: 2,417
A90: En Excel | C90: =SUMAPRODUCTO(t;flujo)/SUMA(flujo)
A91: Explicación | C91: El PPV pondera cada plazo por el flujo nominal, sin descontar.
A94: Ejercicio 66 | B94: Rápido · Duration de cartera
A95: Respuesta | C95: 4.345 | D95: 4,345
A96: En Excel | C96: =40%*2,1+35%*4,8+25%*7,3
A97: Explicación | C97: La duration de una cartera es el promedio de las durations ponderado por el valor de cada posición.
A100: Ejercicio 67 | B100: Rápido · TIR.NO.PER
A101: Respuesta | C101: 0.099037927 | D101: 9,90 %
A102: En Excel | C102: =TIR.NO.PER(flujos;fechas)
A103: Explicación | C103: TIR.NO.PER descuenta cada flujo con (1 + TIR)^(días/365): devuelve una tasa efectiva anual.
A106: Ejercicio 68 | B106: Rápido · Monto a invertir
A107: Respuesta | C107: 29113.64 | D107: $ 29.113,64
A108: En Excel | C108: =72,35/100*40000*(1+0,6%)
A109: Explicación | C109: Monto = precio × cantidad nominal (el precio está por cada 100), más la comisión.
A112: Ejercicio 69 | B112: Rápido · Caución
A113: Respuesta | C113: 2011890.4 | D113: $ 2.011.890,41
A114: En Excel | C114: =2000000*(1+31%*7/365)
A115: Explicación | C115: Interés simple: capital × (1 + TNA × días/365).
A118: Ejercicio 70 | B118: Rápido · TIR nominal → TEA
A119: Respuesta | C119: 0.10381289 | D119: 10,38 %
A120: En Excel | C120: =(1+10%/4)^4-1
A121: Explicación | C121: TEA = (1 + TNA/m)^m − 1.
A124: Ejercicio 71 | B124: Completo · Bullet anual · TIR
A125: Respuesta | C125: =$B$136 | D125: 8,06 %
A126: En Excel | C126: =TIR(flujos) (pagos anuales: ya es efectiva anual)
A127: Explicación | C127: TIR efectiva anual = 8,058 %. Precio = 96,500 · Duration = 3,6169 años · DM = 3,3472 · Convexidad = 14,955 · PPV = 3,6719.
A129: Período | B129: t (años) | C129: Renta | D129: Amort. | E129: Flujo | F129: VA | G129: t · VA | H129: Convexidad | I129: t · Flujo
A130: 0 | B130: 0 | E130: -96.5
A131: 1 | B131: =A131/1 | C131: 7 | D131: 0 | E131: =C131+D131 | F131: =E131/(1+$B$136)^B131 | G131: =B131*F131 | H131: =E131*B131*(B131+1)/(1+$B$136)^(B131+2) | I131: =B131*E131
A132: 2 | B132: =A132/1 | C132: 7 | D132: 0 | E132: =C132+D132 | F132: =E132/(1+$B$136)^B132 | G132: =B132*F132 | H132: =E132*B132*(B132+1)/(1+$B$136)^(B132+2) | I132: =B132*E132
A133: 3 | B133: =A133/1 | C133: 7 | D133: 0 | E133: =C133+D133 | F133: =E133/(1+$B$136)^B133 | G133: =B133*F133 | H133: =E133*B133*(B133+1)/(1+$B$136)^(B133+2) | I133: =B133*E133
A134: 4 | B134: =A134/1 | C134: 7 | D134: 100 | E134: =C134+D134 | F134: =E134/(1+$B$136)^B134 | G134: =B134*F134 | H134: =E134*B134*(B134+1)/(1+$B$136)^(B134+2) | I134: =B134*E134
A136: TIR efectiva anual | B136: =(1+IRR(E130:E134))^1-1
A137: Precio | B137: =SUM(F131:F134)
A138: Duration | B138: =SUM(G131:G134)/B137
A139: DM = D/(1+TIR) | B139: =B138/(1+$B$136)
A140: Convexidad | B140: =SUM(H131:H134)/B137
A141: PPV | B141: =SUM(I131:I134)/SUM(E131:E134)
A144: Ejercicio 72 | B144: Completo · Bullet semestral · TEA
A145: Respuesta | C145: =$B$158 | D145: 8,72 %
...
